koozie/__init__.py
koozie/__main__.py
koozie/cli.py
koozie/koozie.py
koozie-1.3.0.dist-info/LICENSE.txt
koozie-1.3.0.dist-info/METADATA
koozie-1.3.0.dist-info/WHEEL
koozie-1.3.0.dist-info/entry_points.txt
koozie-1.3.0.dist-info/RECORD
