Metadata-Version: 2.1
Name: koozie
Version: 1.3.0
Summary: A light-weight wrapper around pint for unit conversions.
Home-page: https://github.com/bigladder/koozie
License: BSD-3
Keywords: units
Author: Big Ladder Software
Requires-Python: >=3.10,<4.0
Classifier: License :: Other/Proprietary License
Classifier: Programming Language :: Python :: 3
Classifier: Programming Language :: Python :: 3.10
Classifier: Programming Language :: Python :: 3.11
Classifier: Programming Language :: Python :: 3.12
Requires-Dist: click (>=8.1.3,<9.0.0)
Requires-Dist: pint (>=0.24,<0.25)
Project-URL: Repository, https://github.com/bigladder/koozie
